Fomo/__init__.py
Fomo/fomo.py
fomo-1.2.2.dist-info/DESCRIPTION.rst
fomo-1.2.2.dist-info/METADATA
fomo-1.2.2.dist-info/RECORD
fomo-1.2.2.dist-info/WHEEL
fomo-1.2.2.dist-info/metadata.json
fomo-1.2.2.dist-info/top_level.txt
