Metadata-Version: 2.0
Name: fomo
Version: 1.2.2
Summary: Fomo Python SDK is the official SDK wrapper for the Fomo API service
Home-page: https://github.com/usefomo/fomo-python-sdk
Author: Fomo
Author-email: hello@fomo.com
License: MIT
Keywords: fomo notification notifications wrapper api social proof
Platform: UNKNOWN
Classifier: Development Status :: 5 - Production/Stable
Classifier: Intended Audience :: Developers
Classifier: Topic :: Software Development :: Build Tools
Classifier: License :: OSI Approved :: MIT License
Classifier: Programming Language :: Python :: 2.7
Classifier: Programming Language :: Python :: 3
Classifier: Programming Language :: Python :: 3.3
Classifier: Programming Language :: Python :: 3.4
Classifier: Programming Language :: Python :: 3.5
Requires-Dist: requests
Provides-Extra: dev
Requires-Dist: check-manifest; extra == 'dev'
Provides-Extra: test
Requires-Dist: coverage; extra == 'test'
